basejump/alembic.ini
basejump/alembic/README
basejump/alembic/__init__.py
basejump/alembic/env.py
basejump/alembic/script.py.mako
basejump/alembic/utils.py
basejump/alembic/versions/2026_01_10_1458-8b79f44be5c2_create_table_upload_table.py
basejump/core/__init__.py
basejump/core/py.typed
basejump/core/common/__init__.py
basejump/core/common/common_utils.py
basejump/core/common/config/__init__.py
basejump/core/common/config/logconfig.py
basejump/core/common/config/settings.py
basejump/core/database/__init__.py
basejump/core/database/auth.py
basejump/core/database/connector.py
basejump/core/database/db_utils.py
basejump/core/database/manager.py
basejump/core/database/session.py
basejump/core/database/ssl.py
basejump/core/database/vector_utils.py
basejump/core/database/client/__init__.py
basejump/core/database/client/index.py
basejump/core/database/client/query.py
basejump/core/database/client/upload.py
basejump/core/database/crud/__init__.py
basejump/core/database/crud/crud_chat.py
basejump/core/database/crud/crud_connection.py
basejump/core/database/crud/crud_main.py
basejump/core/database/crud/crud_result.py
basejump/core/database/crud/crud_table.py
basejump/core/database/crud/crud_utils.py
basejump/core/database/inspector/__init__.py
basejump/core/database/inspector/athena.py
basejump/core/database/inspector/base.py
basejump/core/database/inspector/mysql.py
basejump/core/database/inspector/postgres.py
basejump/core/database/inspector/redshift.py
basejump/core/database/inspector/snowflake.py
basejump/core/database/inspector/sql_server.py
basejump/core/database/result/__init__.py
basejump/core/database/result/manager.py
basejump/core/database/result/result_utils.py
basejump/core/database/result/store.py
basejump/core/models/__init__.py
basejump/core/models/constants.py
basejump/core/models/enums.py
basejump/core/models/errors.py
basejump/core/models/models.py
basejump/core/models/prompts.py
basejump/core/models/schemas.py
basejump/core/models/ai/__init__.py
basejump_core-0.32.3.dist-info/METADATA
basejump_core-0.32.3.dist-info/WHEEL
basejump_core-0.32.3.dist-info/licenses/LICENSE.md
basejump_core-0.32.3.dist-info/RECORD
