Metadata-Version: 2.4
Name: basejump-core
Version: 0.32.3
Summary: AI data agents to chat with your data
Author-email: Andreas Martinson <andreas.martinson@basejump.ai>
License: AGPL-3.0-or-later
License-File: LICENSE.md
Requires-Python: <3.13,>=3.11
Requires-Dist: aioboto3>=13.2.0
Requires-Dist: aiohttp>=3.11.0
Requires-Dist: aioredis==2.0.1
Requires-Dist: asyncpg>=0.29.0
Requires-Dist: basejump-chat2plot==0.0.11.post1
Requires-Dist: basejump-llama-index-agent-openai==0.4.7.post1
Requires-Dist: basejump-llama-index-embeddings-azure-openai==0.3.2.post1
Requires-Dist: basejump-llama-index-embeddings-openai==0.3.1.post1
Requires-Dist: basejump-llama-index-llms-azure-openai==0.3.2.post1
Requires-Dist: basejump-llama-index-llms-bedrock-converse==0.5.0.post2
Requires-Dist: basejump-llama-index-llms-openai==0.3.39.post2
Requires-Dist: basejump-llama-index-program-openai==0.3.1.post1
Requires-Dist: basejump-llama-index-vector-stores-redis==0.5.1.post2
Requires-Dist: boto3>=1.35.0
Requires-Dist: fastapi>=0.124.0
Requires-Dist: hiredis==2.3.2
Requires-Dist: httpx==0.25.2
Requires-Dist: numpy<2.0.0,>=1.25.2
Requires-Dist: openai==1.76.2
Requires-Dist: pandas<3.0.0,>=2.0.3
Requires-Dist: psycopg2-binary>=2.9.9
Requires-Dist: pyathena>=3.18.0
Requires-Dist: pydantic-settings==2.12.0
Requires-Dist: pydantic>=2.11.0
Requires-Dist: python-dotenv>=1.0.0
Requires-Dist: python-jose==3.3.0
Requires-Dist: python-multipart==0.0.6
Requires-Dist: redis==5.0.3
Requires-Dist: redisvl==0.4.1
Requires-Dist: redshift-connector>=2.1.3
Requires-Dist: requests>=2.32.0
Requires-Dist: rq==2.1.0
Requires-Dist: sentence-transformers==3.4.1
Requires-Dist: snowflake-connector-python>=3.14.0
Requires-Dist: snowflake-sqlalchemy>=1.7.3
Requires-Dist: sqlalchemy>=2.0.23
Requires-Dist: sqlmesh>=0.174.0
